aprsd_email_plugin/__init__.py
aprsd_email_plugin/aprsd_email_plugin.py
aprsd_email_plugin/conf/__init__.py
aprsd_email_plugin/conf/main.py
aprsd_email_plugin/conf/opts.py
aprsd_email_plugin-1.0.0.dist-info/LICENSE
aprsd_email_plugin-1.0.0.dist-info/METADATA
aprsd_email_plugin-1.0.0.dist-info/WHEEL
aprsd_email_plugin-1.0.0.dist-info/entry_points.txt
aprsd_email_plugin-1.0.0.dist-info/top_level.txt
aprsd_email_plugin-1.0.0.dist-info/RECORD
