Metadata-Version: 2.1
Name: aprsd-email-plugin
Version: 1.0.0
Summary: APRSD Email plugin
Author-email: "Walter A. Boring IV" <waboring@hemna.com>
Maintainer-email: "Walter A. Boring IV" <waboring@hemna.com>
License: 
Keywords: aprs,aprs-is,aprsd,aprsd-server,aprsd-client,aprsd-socket,aprsd-socket-server,aprsd-socket-client
Classifier: Development Status :: 5 - Production/Stable
Classifier: Environment :: Console
Classifier: Intended Audience :: Developers
Classifier: Intended Audience :: End Users/Desktop
Classifier: Intended Audience :: Information Technology
Classifier: Topic :: Communications :: Ham Radio
Classifier: Topic :: Internet
Classifier: Programming Language :: Python :: 3 :: Only
Classifier: Programming Language :: Python :: 3
Classifier: Programming Language :: Python :: 3.8
Classifier: Programming Language :: Python :: 3.9
Classifier: Programming Language :: Python :: 3.10
Classifier: Programming Language :: Python :: 3.11
Requires-Python: >=3.8
License-File: LICENSE
Requires-Dist: aprsd>=3.4.4
Requires-Dist: imapclient
Requires-Dist: oslo_config
Provides-Extra: dev
Requires-Dist: pip; extra == "dev"
Requires-Dist: pip-tools; extra == "dev"
Requires-Dist: bump2version; extra == "dev"
Requires-Dist: wheel; extra == "dev"
Requires-Dist: watchdog; extra == "dev"
Requires-Dist: flake8; extra == "dev"
Requires-Dist: tox; extra == "dev"
Requires-Dist: coverage; extra == "dev"
Requires-Dist: Sphinx; extra == "dev"
Requires-Dist: twine; extra == "dev"
Requires-Dist: pytest==6.2.5; extra == "dev"
Requires-Dist: gray; extra == "dev"
